DSD labs/Week-1/Q2b.v
module Q2b(f,a,b,c,d);
input a,b,c,d;
output f;
assign f = (~a&~c&~d)|(~b&d)|(c&d)|(a&b);
endmodule

DSD labs/Week-1/Q2b_tb.v
`timescale 1ns/1ns
`include "Q2b.v"

module Q2b_tb();
reg a,b,c,d;
wire f;

Q2b q2(f,a,b,c,d);
initial begin
	$dumpfile("Q2b_tb.vcd");
	$dumpvars(0,Q2b_tb);
	a=0;b=0;c=0;d=0;#20;
	a=0;b=0;c=0;d=1;#20;
	a=0;b=0;c=1;d=0;#20;
	a=0;b=0;c=1;d=1;#20;
	a=0;b=1;c=0;d=0;#20;
	a=0;b=1;c=0;d=1;#20;
	a=0;b=1;c=1;d=0;#20;
	a=0;b=1;c=0;d=1;#20;
	a=1;b=0;c=0;d=0;#20;
	a=1;b=0;c=0;d=1;#20;
	a=1;b=0;c=1;d=0;#20;
	a=1;b=0;c=1;d=1;#20;
	a=1;b=1;c=0;d=0;#20;
	a=1;b=1;c=0;d=1;#20;
	a=1;b=1;c=1;d=0;#20;
	a=1;b=1;c=0;d=1;#20;
	$display("Test complete");
end
endmodule

DSD labs/Week-1/Q2b_tb.vcd
$date
	Sun Sep 17 23:57:26 2023
$end
$version
	Icarus Verilog
$end
$timescale
	1ns
$end
$scope module Q2b_tb $end
$var wire 1 ! f $end
$var reg 1 " a $end
$var reg 1 # b $end
$var reg 1 $ c $end
$var reg 1 % d $end
$scope module q2 $end
$var wire 1 " a $end
$var wire 1 # b $end
$var wire 1 $ c $end
$var wire 1 % d $end
$var wire 1 ! f $end
$upscope $end
$upscope $end
$enddefinitions $end
#0
$dumpvars
0%
0$
0#
0"
1!
$end
#20
1%
#40
0!
0%
1$
#60
1!
1%
#80
1!
0%
0$
1#
#100
0!
1%
#120
0%
1$
#140
1%
0$
#160
0%
0#
1"
#180
1!
1%
#200
0!
0%
1$
#220
1!
1%
#240
0%
0$
1#
#260
1%
#280
0%
1$
#300
1%
0$
