Week-2/Q2a.v
module Q2a(A,B,C,D,f);
input A,B,C,D;
output f;
assign f = (C|D)&(B|C)&(~A|~B|~C|~D);
endmodule

Week-2/Q2a_tb.v
`timescale 1ns/1ns
`include "Q2a.v"

module Q2a_tb;
reg A,B,C,D;
wire f;

Q2a q2(A,B,C,D,f);
initial begin

	$dumpfile("Q2a_tb.vcd");
	$dumpvars(0,Q2a_tb);
	
	A=0;B=0;C=0;D=0;#20;
	A=0;B=0;C=0;D=1;#20;
	A=0;B=0;C=1;D=0;#20;
	A=0;B=0;C=1;D=1;#20;
	A=0;B=1;C=0;D=0;#20;
	A=0;B=1;C=0;D=1;#20;
	A=0;B=1;C=1;D=0;#20;
	A=0;B=1;C=1;D=1;#20;
	A=1;B=0;C=0;D=0;#20;
	A=1;B=0;C=0;D=1;#20;
	A=1;B=0;C=1;D=0;#20;
	A=1;B=0;C=1;D=1;#20;
	A=1;B=1;C=0;D=0;#20;
	A=1;B=1;C=0;D=1;#20;
	A=1;B=1;C=1;D=0;#20;
	A=1;B=1;C=1;D=1;#20;
	
	$display("Test complete");
	
end

endmodule

Week-2/Q2a_tb.vcd
$date
	Thu Aug 10 09:51:15 2023
$end
$version
	Icarus Verilog
$end
$timescale
	1ns
$end
$scope module Q2a_tb $end
$var wire 1 ! f $end
$var reg 1 " A $end
$var reg 1 # B $end
$var reg 1 $ C $end
$var reg 1 % D $end
$scope module q2 $end
$var wire 1 " A $end
$var wire 1 # B $end
$var wire 1 $ C $end
$var wire 1 % D $end
$var wire 1 ! f $end
$upscope $end
$upscope $end
$enddefinitions $end
#0
$dumpvars
0%
0$
0#
0"
0!
$end
#20
1%
#40
1!
0%
1$
#60
1%
#80
0!
0%
0$
1#
#100
1!
1%
#120
0%
1$
#140
1%
#160
0!
0%
0$
0#
1"
#180
1%
#200
1!
0%
1$
#220
1%
#240
0!
0%
0$
1#
#260
1!
1%
#280
0%
1$
#300
0!
1%
