Week-2/Q2b.v
module Q2b(A,B,C,D,f);
input A,B,C,D;
output f;
assign f = (~C|D)&(~A|D)&(A|~B|C|~D);
endmodule

DSD labs/Week-2/Q2b_tb.v
`timescale 1ns/1ns
`include "Q2b.v"

module Q2b_tb;
reg A,B,C,D;
wire f;

Q2b q2(A,B,C,D,f);
initial begin

	$dumpfile("Q2b_tb.vcd");
	$dumpvars(0,Q2b_tb);
	
	A=0;B=0;C=0;D=0;#20;
	A=0;B=0;C=0;D=1;#20;
	A=0;B=0;C=1;D=0;#20;
	A=0;B=0;C=1;D=1;#20;
	A=0;B=1;C=0;D=0;#20;
	A=0;B=1;C=0;D=1;#20;
	A=0;B=1;C=1;D=0;#20;
	A=0;B=1;C=1;D=1;#20;
	A=1;B=0;C=0;D=0;#20;
	A=1;B=0;C=0;D=1;#20;
	A=1;B=0;C=1;D=0;#20;
	A=1;B=0;C=1;D=1;#20;
	A=1;B=1;C=0;D=0;#20;
	A=1;B=1;C=0;D=1;#20;
	A=1;B=1;C=1;D=0;#20;
	A=1;B=1;C=1;D=1;#20;
	
	$display("Test complete");
	
end

endmodule

Week-2/Q2b_tb.vcd
$date
	Thu Aug 10 09:53:50 2023
$end
$version
	Icarus Verilog
$end
$timescale
	1ns
$end
$scope module Q2b_tb $end
$var wire 1 ! f $end
$var reg 1 " A $end
$var reg 1 # B $end
$var reg 1 $ C $end
$var reg 1 % D $end
$scope module q2 $end
$var wire 1 " A $end
$var wire 1 # B $end
$var wire 1 $ C $end
$var wire 1 % D $end
$var wire 1 ! f $end
$upscope $end
$upscope $end
$enddefinitions $end
#0
$dumpvars
0%
0$
0#
0"
1!
$end
#20
1%
#40
0!
0%
1$
#60
1!
1%
#80
0%
0$
1#
#100
0!
1%
#120
0%
1$
#140
1!
1%
#160
0!
0%
0$
0#
1"
#180
1!
1%
#200
0!
0%
1$
#220
1!
1%
#240
0!
0%
0$
1#
#260
1!
1%
#280
0!
0%
1$
#300
1!
1%
