Week-10/Up_Counter/upc.v
module upc(clk,clear,Q);
input clk,clear;
output [3:0]Q;
jkff s0(1'b1,1'b1,clk,clear,Q[0]);
jkff s1(1'b1,1'b1,Q[0],clear,Q[1]);
jkff s2(1'b1,1'b1,Q[1],clear,Q[2]);
jkff s3(1'b1,1'b1,Q[2],clear,Q[3]);
endmodule


module jkff(J,K,clk,resetn,Q);
input J,K,clk,resetn;
output reg Q;
always @(negedge clk)
begin
	if (resetn)
		Q<=0;
	else
		Q<=(J&~Q)|(~K&Q);
end
endmodule

Week-10/Up_Counter/upc_tb.v
`timescale 1ns/1ns
`include "upc.v"

module upc_tb();
reg clk,clear;
wire [3:0]Q;

upc upc1(clk,clear,Q);
initial begin
	$dumpfile("upc_tb.vcd");
	$dumpvars(0,upc_tb);
	clk=1;
	forever #20 clk=~clk;
end
initial begin
	clear=1;#40;
	clear=0;#320;
	$display("Test complete");
	$finish;
end
endmodule

DSD labs/Week-10/Up_Counter/upc_tb.vcd
$date
	Thu Oct 26 10:45:34 2023
$end
$version
	Icarus Verilog
$end
$timescale
	1ns
$end
$scope module upc_tb $end
$var wire 4 ! Q [3:0] $end
$var reg 1 " clear $end
$var reg 1 # clk $end
$scope module upc1 $end
$var wire 1 " clear $end
$var wire 1 # clk $end
$var wire 4 $ Q [3:0] $end
$scope module s0 $end
$var wire 1 % J $end
$var wire 1 & K $end
$var wire 1 # clk $end
$var wire 1 " resetn $end
$var reg 1 ' Q $end
$upscope $end
$scope module s1 $end
$var wire 1 ( J $end
$var wire 1 ) K $end
$var wire 1 * clk $end
$var wire 1 " resetn $end
$var reg 1 + Q $end
$upscope $end
$scope module s2 $end
$var wire 1 , J $end
$var wire 1 - K $end
$var wire 1 . clk $end
$var wire 1 " resetn $end
$var reg 1 / Q $end
$upscope $end
$scope module s3 $end
$var wire 1 0 J $end
$var wire 1 1 K $end
$var wire 1 2 clk $end
$var wire 1 " resetn $end
$var reg 1 3 Q $end
$upscope $end
$upscope $end
$upscope $end
$enddefinitions $end
#0
$dumpvars
x3
x2
11
10
x/
x.
1-
1,
x+
x*
1)
1(
x'
1&
1%
bx $
1#
1"
bx !
$end
#20
03
02
0/
0.
0+
0*
b0 !
b0 $
0'
0#
#40
1#
0"
#60
1*
b1 !
b1 $
1'
0#
#80
1#
#100
1.
1+
0*
b10 !
b10 $
0'
0#
#120
1#
#140
1*
b11 !
b11 $
1'
0#
#160
1#
#180
12
1/
0.
0+
0*
b100 !
b100 $
0'
0#
#200
1#
#220
1*
b101 !
b101 $
1'
0#
#240
1#
#260
1.
1+
0*
b110 !
b110 $
0'
0#
#280
1#
#300
1*
b111 !
b111 $
1'
0#
#320
1#
#340
13
02
0/
0.
0+
0*
b1000 !
b1000 $
0'
0#
