DSD labs/Week-5/Encoder16_4.v
module Encoder16_4(w, y, z);
    input [15:0] w;
    output reg [3:0] y;
    output reg z;
    integer k;

    always @(w)
    begin
        y = 4'b0000;
        z = 1;
        if (w == 0)
        begin
            z = 0;
            y = 4'bXXXX;
        end
        else
        begin
            for (k = 0; k <= 15; k = k + 1)
	    begin
                if (w[k] == 1)
                    y = k;
	    end
        end
    end
endmodule

DSD labs/Week-5/Encoder16_4_tb.v
`timescale 1ns/1ns
`include "Encoder16_4.v"

module Encoder16_4_tb;
    reg [15:0] w;
    wire [3:0] y;
    wire z;


Encoder16_4 q(w, y, z);

initial begin
        $dumpfile("Encoder16_4_tb.vcd");
        $dumpvars(0, Encoder16_4_tb);


        w = 16'b0000000000000000; #20;
        w = 16'b0000000000000010; #20;
        w = 16'b0000000000000100; #20;
        w = 16'b0000000000001000; #20;
        w = 16'b0000000000010000; #20;
        w = 16'b0000000000100000; #20;
        w = 16'b0000000001000000; #20;
        w = 16'b0000000010000000; #20;
        w = 16'b0000000100000000; #20;
        w = 16'b0000001000000000; #20;
        w = 16'b0000010000000000; #20;
        w = 16'b0000100000000000; #20;
        w = 16'b0001000000000000; #20;
        w = 16'b0010000000000000; #20;
        w = 16'b0100000000000000; #20;
        w = 16'b1000000000000000; #20;

        $display("Test Complete");
    end
endmodule

Week-5/Encoder16_4_tb.vcd
$date
	Thu Aug 31 10:41:26 2023
$end
$version
	Icarus Verilog
$end
$timescale
	1ns
$end
$scope module Encoder16_4_tb $end
$var wire 1 ! z $end
$var wire 4 " y [3:0] $end
$var reg 16 # w [15:0] $end
$scope module q $end
$var wire 16 $ w [15:0] $end
$var reg 4 % y [3:0] $end
$var reg 1 ! z $end
$var integer 32 & k [31:0] $end
$upscope $end
$upscope $end
$enddefinitions $end
#0
$dumpvars
bx &
bx %
b0 $
b0 #
bx "
0!
$end
#20
b10000 &
1!
b1 "
b1 %
b10 #
b10 $
#40
b10000 &
b10 "
b10 %
b100 #
b100 $
#60
b10000 &
b11 "
b11 %
b1000 #
b1000 $
#80
b10000 &
b100 "
b100 %
b10000 #
b10000 $
#100
b10000 &
b101 "
b101 %
b100000 #
b100000 $
#120
b10000 &
b110 "
b110 %
b1000000 #
b1000000 $
#140
b10000 &
b111 "
b111 %
b10000000 #
b10000000 $
#160
b10000 &
b1000 "
b1000 %
b100000000 #
b100000000 $
#180
b10000 &
b1001 "
b1001 %
b1000000000 #
b1000000000 $
#200
b10000 &
b1010 "
b1010 %
b10000000000 #
b10000000000 $
#220
b10000 &
b1011 "
b1011 %
b100000000000 #
b100000000000 $
#240
b10000 &
b1100 "
b1100 %
b1000000000000 #
b1000000000000 $
#260
b10000 &
b1101 "
b1101 %
b10000000000000 #
b10000000000000 $
#280
b10000 &
b1110 "
b1110 %
b100000000000000 #
b100000000000000 $
#300
b10000 &
b1111 "
b1111 %
b1000000000000000 #
b1000000000000000 $
