DSD labs/Week-11(lab-10)/Q1.v
module jkff(Q,j,k,clear,clk);
input j,k,clear,clk;
output reg Q;
always@(posedge clk)
begin
	if(clear==1)
		Q<=0;
	else
		Q<=(j&~Q)|(~k&Q);
end
endmodule


//A=Q[2],B=Q[1],C=Q[0]
module Q1(clear,clk,Q);
input clear,clk;
output [2:0]Q;
jkff ff2(Q[2],Q[1],(Q[1]&Q[0]),clear,clk);
jkff ff1(Q[1],Q[0],(~Q[2]|Q[0]),clear,clk);
jkff ff0(Q[0],(Q[2]|~Q[1]),1'b1,clear,clk);
endmodule

DSD labs/Week-11(lab-10)/Q1_tb.v
`timescale 1ns/1ns
`include "Q1.v"
module Q1_tb();
reg clk,clear;
wire [2:0]Q;
Q1 q1(clear,clk,Q);
initial begin
	$dumpfile("Q1_tb.vcd");
	$dumpvars(0,Q1_tb);
	clk=1;
	forever #10 clk=~clk;
end
initial begin
	clear=1;#20;
	clear=0;#400;
	$display("Test complete");
	$finish;
end
endmodule

Week-11(lab-10)/Q1_tb.vcd
$date
	Thu Nov  2 09:58:33 2023
$end
$version
	Icarus Verilog
$end
$timescale
	1ns
$end
$scope module Q1_tb $end
$var wire 3 ! Q [2:0] $end
$var reg 1 " clear $end
$var reg 1 # clk $end
$scope module q1 $end
$var wire 1 " clear $end
$var wire 1 # clk $end
$var wire 3 $ Q [2:0] $end
$scope module ff0 $end
$var wire 1 " clear $end
$var wire 1 # clk $end
$var wire 1 % j $end
$var wire 1 & k $end
$var reg 1 ' Q $end
$upscope $end
$scope module ff1 $end
$var wire 1 " clear $end
$var wire 1 # clk $end
$var wire 1 ( j $end
$var wire 1 ) k $end
$var reg 1 * Q $end
$upscope $end
$scope module ff2 $end
$var wire 1 " clear $end
$var wire 1 # clk $end
$var wire 1 + j $end
$var wire 1 , k $end
$var reg 1 - Q $end
$upscope $end
$upscope $end
$upscope $end
$enddefinitions $end
#0
$dumpvars
0-
0,
0+
0*
1)
0(
0'
1&
1%
b0 $
1#
1"
b0 !
$end
#10
0#
#20
1(
b1 !
b1 $
1'
1#
0"
#30
0#
#40
0%
1+
0(
1*
b10 !
b10 $
0'
1#
#50
0#
#60
0)
1%
0+
0*
b100 !
b100 $
1-
1#
#70
0#
#80
1)
1(
b101 !
b101 $
1'
1#
#90
0#
#100
0)
0(
1+
0'
b110 !
b110 $
1*
1#
#110
0#
#120
1)
1,
1(
b111 !
b111 $
1'
1#
#130
0#
#140
0,
1%
0(
0+
0'
0*
b0 !
b0 $
0-
1#
#150
0#
#160
1(
b1 !
b1 $
1'
1#
#170
0#
#180
0%
0(
1+
0'
b10 !
b10 $
1*
1#
#190
0#
#200
0)
1%
0+
1-
b100 !
b100 $
0*
1#
#210
0#
#220
1)
1(
b101 !
b101 $
1'
1#
#230
0#
#240
0)
1+
0(
1*
b110 !
b110 $
0'
1#
#250
0#
#260
1)
1,
1(
b111 !
b111 $
1'
1#
#270
0#
#280
1)
0,
0+
0(
0-
0*
b0 !
b0 $
0'
1#
#290
0#
#300
1(
b1 !
b1 $
1'
1#
#310
0#
#320
0%
1+
0(
1*
b10 !
b10 $
0'
1#
#330
0#
#340
0)
1%
0+
0*
b100 !
b100 $
1-
1#
#350
0#
#360
1)
1(
b101 !
b101 $
1'
1#
#370
0#
#380
0)
0(
1+
0'
b110 !
b110 $
1*
1#
#390
0#
#400
1)
1,
1(
b111 !
b111 $
1'
1#
#410
0#
#420
0,
1%
0(
0+
0'
0*
b0 !
b0 $
0-
1#
