Week-11(lab-10)/Q3.v
module tff(Q,T,clear,clk);
input T,clear,clk;
output reg Q;
always@(posedge clk)
begin
	if(clear==1)
		Q<=0;
	else
		Q<=Q^T;
end
endmodule

module Q3(clear,clk,Q);
input clear,clk;
output [2:0]Q;
tff ff2(Q[2],(Q[2]^Q[1]),clear,clk);
tff ff1(Q[1],(Q[1]^Q[0]),clear,clk);
tff ff0(Q[0],~(Q[2]^Q[0]),clear,clk);
endmodule

DSD labs/Week-11(lab-10)/Q3_tb.v
`timescale 1ns/1ns
`include "Q3.v"
module Q3_tb();
reg clk,clear;
wire [2:0]Q;
Q3 q3(clear,clk,Q);
initial begin
	$dumpfile("Q3_tb.vcd");
	$dumpvars(0,Q3_tb);
	clk=1;
	forever #10 clk=~clk;
end
initial begin
	clear=1;#20;
	clear=0;#400;
	$display("Test complete");
	$finish;
end
endmodule

Week-11(lab-10)/Q3_tb.vcd
$date
	Thu Nov  2 11:10:29 2023
$end
$version
	Icarus Verilog
$end
$timescale
	1ns
$end
$scope module Q3_tb $end
$var wire 3 ! Q [2:0] $end
$var reg 1 " clear $end
$var reg 1 # clk $end
$scope module q3 $end
$var wire 1 " clear $end
$var wire 1 # clk $end
$var wire 3 $ Q [2:0] $end
$scope module ff0 $end
$var wire 1 % T $end
$var wire 1 " clear $end
$var wire 1 # clk $end
$var reg 1 & Q $end
$upscope $end
$scope module ff1 $end
$var wire 1 ' T $end
$var wire 1 " clear $end
$var wire 1 # clk $end
$var reg 1 ( Q $end
$upscope $end
$scope module ff2 $end
$var wire 1 ) T $end
$var wire 1 " clear $end
$var wire 1 # clk $end
$var reg 1 * Q $end
$upscope $end
$upscope $end
$upscope $end
$enddefinitions $end
#0
$dumpvars
0*
0)
0(
0'
0&
1%
b0 $
1#
1"
b0 !
$end
#10
0#
#20
0%
1'
b1 !
b1 $
1&
1#
0"
#30
0#
#40
0'
1)
b11 !
b11 $
1(
1#
#50
0#
#60
1%
0)
b111 !
b111 $
1*
1#
#70
0#
#80
0%
1'
b110 !
b110 $
0&
1#
#90
0#
#100
0'
1)
b100 !
b100 $
0(
1#
#110
0#
#120
1%
0)
b0 !
b0 $
0*
1#
#130
0#
#140
0%
1'
b1 !
b1 $
1&
1#
#150
0#
#160
0'
1)
b11 !
b11 $
1(
1#
#170
0#
#180
1%
0)
b111 !
b111 $
1*
1#
#190
0#
#200
0%
1'
b110 !
b110 $
0&
1#
#210
0#
#220
0'
1)
b100 !
b100 $
0(
1#
#230
0#
#240
1%
0)
b0 !
b0 $
0*
1#
#250
0#
#260
0%
1'
b1 !
b1 $
1&
1#
#270
0#
#280
0'
1)
b11 !
b11 $
1(
1#
#290
0#
#300
1%
0)
b111 !
b111 $
1*
1#
#310
0#
#320
0%
1'
b110 !
b110 $
0&
1#
#330
0#
#340
0'
1)
b100 !
b100 $
0(
1#
#350
0#
#360
1%
0)
b0 !
b0 $
0*
1#
#370
0#
#380
0%
1'
b1 !
b1 $
1&
1#
#390
0#
#400
0'
1)
b11 !
b11 $
1(
1#
#410
0#
#420
1%
0)
b111 !
b111 $
1*
1#
