DSD labs/Week-3/Q2.v
module Q2(cin, x, y, s, cout);
input cin, x, y; 
output s, cout;
assign s = x^y^cin;
assign cout = (x&y)|(x&cin)|(y&cin);
endmodule

Week-3/Q2_tb.v
`timescale 1ns/1ns
`include "Q2.v"

module Q2_tb;
reg cin, x, y;
wire s,cout;

Q2 q2(cin,x,y,s,cout);
initial begin

	$dumpfile("Q2_tb.vcd");
	$dumpvars(0,Q2_tb);
	
	cin=0;x=0;y=0;#20;
	cin=0;x=0;y=1;#20;
	cin=0;x=1;y=0;#20;
	cin=0;x=1;y=1;#20;
	cin=1;x=0;y=0;#20;
	cin=1;x=0;y=1;#20;
	cin=1;x=1;y=0;#20;
	cin=1;x=1;y=1;#20;
	
	$display("Test complete");
	
end

endmodule

Week-3/Q2_tb.vcd
$date
	Thu Aug 17 09:48:32 2023
$end
$version
	Icarus Verilog
$end
$timescale
	1ns
$end
$scope module Q2_tb $end
$var wire 1 ! s $end
$var wire 1 " cout $end
$var reg 1 # cin $end
$var reg 1 $ x $end
$var reg 1 % y $end
$scope module q2 $end
$var wire 1 # cin $end
$var wire 1 " cout $end
$var wire 1 ! s $end
$var wire 1 $ x $end
$var wire 1 % y $end
$upscope $end
$upscope $end
$enddefinitions $end
#0
$dumpvars
0%
0$
0#
0"
0!
$end
#20
1!
1%
#40
0%
1$
#60
1"
0!
1%
#80
0"
1!
0%
0$
1#
#100
0!
1"
1%
#120
0%
1$
#140
1!
1%
