Week-4/mux16to1.v
module mux16to1(W,S,f);
input [0:15]W;
input [3:0]S;
output f;
wire [0:1]M;
mux8to1 m1(W[0:7],S[2:0],M[0]);
mux8to1 m2(W[8:15],S[2:0],M[1]);
mux2to1 m3(M[0:1], S[3], f);
endmodule



module mux2to1(W,S,f);
input [0:1]W;
input S;
output reg f;
always@(W or S)
case (S)
1'b0: f=W[0];
1'b1: f=W[1];
endcase
endmodule



module mux8to1(W,S,f);
input [0:7]W;
input [2:0]S;
output reg f;

always@(W or S)
case (S)
3'b000: f=W[0];
3'b001: f=W[1];
3'b010: f=W[2];
3'b011: f=W[3];
3'b100: f=W[4];
3'b101: f=W[5];
3'b110: f=W[6];
3'b111: f=W[7];
endcase
endmodule

DSD labs/Week-4/mux16to1_tb.v
`timescale 1ns/1ns
`include "mux16to1.v"

module mux16to1_tb;
reg [0:15]W;
reg [3:0]S;
wire f;

mux16to1 m1(W,S,f);
initial begin
	$dumpfile("mux16to1_tb.vcd");
	$dumpvars(0,mux16to1_tb);
	
	W=16'b1001100110011001;
	S=4'b0000;#20;
	S=4'b0001;#20;
	S=4'b0010;#20;
	S=4'b0011;#20;
	S=4'b0100;#20;
	S=4'b0101;#20;
	S=4'b0110;#20;
	S=4'b0111;#20;
	S=4'b1000;#20;
	S=4'b1001;#20;
	S=4'b1010;#20;
	S=4'b1011;#20;
	S=4'b1100;#20;
	S=4'b1101;#20;
	S=4'b1110;#20;
	S=4'b1111;#20;
				
	$display("Test complete");
end
endmodule

Week-4/mux16to1_tb.vcd
$date
	Thu Aug 24 09:59:43 2023
$end
$version
	Icarus Verilog
$end
$timescale
	1ns
$end
$scope module mux16to1_tb $end
$var wire 1 ! f $end
$var reg 4 " S [3:0] $end
$var reg 16 # W [0:15] $end
$scope module m1 $end
$var wire 4 $ S [3:0] $end
$var wire 16 % W [0:15] $end
$var wire 1 ! f $end
$var wire 2 & M [0:1] $end
$scope module m1 $end
$var wire 3 ' S [2:0] $end
$var wire 8 ( W [0:7] $end
$var reg 1 ) f $end
$upscope $end
$scope module m2 $end
$var wire 3 * S [2:0] $end
$var wire 8 + W [0:7] $end
$var reg 1 , f $end
$upscope $end
$scope module m3 $end
$var wire 1 - S $end
$var wire 2 . W [0:1] $end
$var reg 1 ! f $end
$upscope $end
$upscope $end
$upscope $end
$enddefinitions $end
#0
$dumpvars
b11 .
0-
1,
b10011001 +
b0 *
1)
b10011001 (
b0 '
b11 &
b1001100110011001 %
b0 $
b1001100110011001 #
b0 "
1!
$end
#20
0!
0)
b0 &
b0 .
0,
b1 '
b1 *
b1 "
b1 $
#40
b10 '
b10 *
b10 "
b10 $
#60
1!
1)
b11 &
b11 .
1,
b11 '
b11 *
b11 "
b11 $
#80
b100 '
b100 *
b100 "
b100 $
#100
0!
0)
b0 &
b0 .
0,
b101 '
b101 *
b101 "
b101 $
#120
b110 '
b110 *
b110 "
b110 $
#140
1!
1)
b11 &
b11 .
1,
b111 '
b111 *
b111 "
b111 $
#160
b0 '
b0 *
1-
b1000 "
b1000 $
#180
0!
0)
b0 &
b0 .
0,
b1 '
b1 *
b1001 "
b1001 $
#200
b10 '
b10 *
b1010 "
b1010 $
#220
1!
1)
b11 &
b11 .
1,
b11 '
b11 *
b1011 "
b1011 $
#240
b100 '
b100 *
b1100 "
b1100 $
#260
0!
0)
b0 &
b0 .
0,
b101 '
b101 *
b1101 "
b1101 $
#280
b110 '
b110 *
b1110 "
b1110 $
#300
1!
1)
b11 &
b11 .
1,
b111 '
b111 *
b1111 "
b1111 $
