Midsem practice/f0.v
module mux4to1(w,s,f);
input [0:3]w;
input [1:0]s;
output reg f;
always@(s or w)
begin
if(s==0)
f=w[0];
else if(s==1)
f=w[1];
else if(s==2)
f=w[2];
else
f=w[3];
end
endmodule

module f0(a,b,c,d,g);
input a,b,c,d;
output g;
wire [0:3]m0;
wire [1:0]m1;
assign w = {c,~c&d,d,1'b0};
assign s = {a,b};
mux4to1 mux1(m0[0:3],m1[1:0],g);
endmodule

Midsem practice/f0_tb.v
`timescale 1ns/1ns
`include "f0.v"

module f0_tb();
reg a,b,c,d;
wire g;

f0 stg0(a,b,c,d,g);
initial begin
	$dumpfile("f0_tb.vcd");
	$dumpvars(0,f0_tb);
	a=0;b=0;c=0;d=0;#20;
	a=0;b=0;c=0;d=1;#20;
	a=0;b=0;c=1;d=0;#20;
	a=0;b=0;c=1;d=1;#20;
	a=0;b=1;c=0;d=0;#20;
	a=0;b=1;c=0;d=1;#20;
	a=0;b=1;c=1;d=0;#20;
	a=0;b=1;c=1;d=1;#20;
	a=1;b=0;c=0;d=0;#20;
	a=1;b=0;c=0;d=1;#20;
	a=1;b=0;c=1;d=0;#20;
	a=1;b=0;c=1;d=1;#20;
	a=1;b=1;c=0;d=0;#20;
	a=1;b=1;c=0;d=1;#20;
	a=1;b=1;c=1;d=0;#20;
	a=1;b=1;c=1;d=1;#20;
	$display("Test complete");
end
endmodule

Midsem practice/f0_tb.vcd
$date
	Tue Sep 26 19:03:31 2023
$end
$version
	Icarus Verilog
$end
$timescale
	1ns
$end
$scope module f0_tb $end
$var wire 1 ! g $end
$var reg 1 " a $end
$var reg 1 # b $end
$var reg 1 $ c $end
$var reg 1 % d $end
$scope module stg0 $end
$var wire 1 " a $end
$var wire 1 # b $end
$var wire 1 $ c $end
$var wire 1 % d $end
$var wire 4 & m0 [0:3] $end
$var wire 2 ' m1 [1:0] $end
$var wire 1 ( w $end
$var wire 1 ) s $end
$var wire 1 ! g $end
$scope module mux1 $end
$var wire 2 * s [1:0] $end
$var wire 4 + w [0:3] $end
$var reg 1 ! f $end
$upscope $end
$upscope $end
$upscope $end
$enddefinitions $end
#0
$dumpvars
bz +
bz *
0)
0(
bz '
bz &
0%
0$
0#
0"
z!
$end
#20
1%
#40
0%
1$
#60
1%
#80
1)
0%
0$
1#
#100
1%
#120
0%
1$
#140
1%
#160
0)
0%
0$
0#
1"
#180
1%
#200
0%
1$
#220
1%
#240
1)
0%
0$
1#
#260
1%
#280
0%
1$
#300
1%
