Midsem practice/full_adder.v
/*module full_adder(cin,x,y,s,cout);
input cin,x,y;
output s,cout;
assign s = cin^x^y;
assign cout = (cin&x)|(cin&y)|(x&y);
endmodule*/

//full_adder using half_adders

module half_adder(x,y,c,s);
input x,y;
output c,s;
assign c = x&y;
assign s = x^y;
endmodule

module full_adder(cin,x,y,s,cout);
input cin,x,y;
output s,cout;
wire m1,m2,m3;
half_adder h1(cin,x,

Week-3/Q3.v
module Q3(ctrl, X, Y, S, carryout);
input ctrl;
input [3:0] X, Y;
output [3:0]S;
output carryout;
wire [3:0]Yc;
wire [3:1]C;
assign Yc[3] = Y[3] ^ ctrl;
assign Yc[2] = Y[2] ^ ctrl;
assign Yc[1] = Y[1] ^ ctrl;
assign Yc[0] = Y[0] ^ ctrl;
full_adder s0(ctrl, X[0], Yc[0], S[0], C[1]);
full_adder s1(C[1], X[1], Yc[1], S[1], C[2]);
full_adder s2(C[2], X[2], Yc[2], S[2], C[3]);
full_adder s3(C[3], X[3], Yc[3], S[3], carryout);
endmodule

module full_adder(cin, x, y, s, cout);
input cin, x, y; 
output s, cout;
assign s = x^y^cin;
assign cout = (x&y)|(x&cin)|(y&cin);
endmodule

Midsem practice/full_adder_tb.v
`timescale 1ns/1ns
`include "full_adder.v"

module full_adder_tb();
reg cin,x,y;
wire s,cout;

full_adder fa1(cin,x,y,s,cout);
initial begin
	$dumpfile("full_adder_tb.vcd");
	$dumpvars(0,full_adder_tb);
	cin=0;x=0;y=0;#20;
	cin=0;x=0;y=1;#20;
	cin=0;x=1;y=0;#20;
	cin=0;x=1;y=1;#20;
	cin=1;x=0;y=0;#20;
	cin=1;x=0;y=1;#20;
	cin=1;x=1;y=0;#20;
	cin=1;x=1;y=1;#20;
	$display("Test complete");
end
endmodule

Midsem practice/full_adder_tb.vcd
$date
	Tue Sep 26 17:01:36 2023
$end
$version
	Icarus Verilog
$end
$timescale
	1ns
$end
$scope module full_adder_tb $end
$var wire 1 ! s $end
$var wire 1 " cout $end
$var reg 1 # cin $end
$var reg 1 $ x $end
$var reg 1 % y $end
$scope module fa1 $end
$var wire 1 # cin $end
$var wire 1 " cout $end
$var wire 1 ! s $end
$var wire 1 $ x $end
$var wire 1 % y $end
$upscope $end
$upscope $end
$enddefinitions $end
#0
$dumpvars
0%
0$
0#
0"
0!
$end
#20
1!
1%
#40
0%
1$
#60
1"
0!
1%
#80
0"
1!
0%
0$
1#
#100
1"
0!
1%
#120
0%
1$
#140
1!
1%
