Midsem practice/test.v
module test(a,b,c,f);
input a,b,c;
output f;
assign f = (a&b&c);
endmodule

Midsem practice/test_tb.v
`timescale 1ns/1ns
`include "test.v"

module test_tb();
reg a,b,c;
wire f;

test t1(a,b,c,f);
initial begin
    $dumpfile("test_tb.vcd");
    $dumpvars(0,test_tb);

    a=0;b=0;c=0;#20;
    a=0;b=0;c=1;#20;
    a=0;b=1;c=0;#20;
    a=0;b=1;c=1;#20;
    a=1;b=0;c=0;#20;
    a=1;b=0;c=1;#20;
    a=1;b=1;c=0;#20;
    a=1;b=1;c=1;#20;

    $display("Test complete");
end
endmodule

Midsem practice/test_tb.vcd
$date
	Wed Oct 11 19:34:32 2023
$end
$version
	Icarus Verilog
$end
$timescale
	1ns
$end
$scope module test_tb $end
$var wire 1 ! f $end
$var reg 1 " a $end
$var reg 1 # b $end
$var reg 1 $ c $end
$scope module t1 $end
$var wire 1 " a $end
$var wire 1 # b $end
$var wire 1 $ c $end
$var wire 1 ! f $end
$upscope $end
$upscope $end
$enddefinitions $end
#0
$dumpvars
0$
0#
0"
0!
$end
#20
1$
#40
0$
1#
#60
1$
#80
0$
0#
1"
#100
1$
#120
0$
1#
#140
1!
1$
