DSD labs/input3dec.v
module dec2to4(w,en,y);
input [1:0]w;
input en;
output reg [0:3]y;
integer k;

always@(w or en)
begin
	y=4'b0000;
	if (en==1)
	begin
		for(k=0; k<=3;k++)
		if (w==k)
			y[k]=1;
	end
end
endmodule


module input3dec(w,f);
input [2:0]w;
output f;
wire [0:7]m;

dec2to4 d1(w[1:0],~w[2],m[0:3]);
dec2to4 d2(w[1:0],w[2],m[4:7]);
assign f = (m[3]|m[5]|m[6]|m[7]);
endmodule

DSD labs/input3dec_tb.v
`timescale 1ns/1ns
`include "input3dec.v"

module input3dec_tb();
reg [2:0]w;
wire f;

input3dec d1(w,f);
initial begin
	$dumpfile("input3dec_tb.vcd");
	$dumpvars(0,input3dec_tb);
	w=3'b000;#20;
	w=3'b001;#20;
	w=3'b010;#20;
	w=3'b011;#20;
	w=3'b100;#20;
	w=3'b101;#20;
	w=3'b110;#20;
	w=3'b111;#20;
	$display("Test complete");
end
endmodule

DSD labs/input3dec_tb.vcd
$date
	Thu Sep 21 00:26:33 2023
$end
$version
	Icarus Verilog
$end
$timescale
	1ns
$end
$scope module input3dec_tb $end
$var wire 1 ! f $end
$var reg 3 " w [2:0] $end
$scope module d1 $end
$var wire 1 ! f $end
$var wire 3 # w [2:0] $end
$var wire 8 $ m [0:7] $end
$scope module d1 $end
$var wire 1 % en $end
$var wire 2 & w [1:0] $end
$var reg 4 ' y [0:3] $end
$var integer 32 ( k [31:0] $end
$upscope $end
$scope module d2 $end
$var wire 1 ) en $end
$var wire 2 * w [1:0] $end
$var reg 4 + y [0:3] $end
$var integer 32 , k [31:0] $end
$upscope $end
$upscope $end
$upscope $end
$enddefinitions $end
#0
$dumpvars
bx ,
b0 +
b0 *
0)
b100 (
b1000 '
b0 &
1%
b10000000 $
b0 #
b0 "
0!
$end
#20
b100 (
b1000000 $
b100 '
b1 &
b1 *
b1 "
b1 #
#40
b100 (
b100000 $
b10 '
b10 &
b10 *
b10 "
b10 #
#60
1!
b100 (
b10000 $
b1 '
b11 &
b11 *
b11 "
b11 #
#80
0!
b0 '
0%
b1000 $
b1000 +
b100 ,
b0 &
b0 *
1)
b100 "
b100 #
#100
1!
b100 ,
b100 $
b100 +
b1 &
b1 *
b101 "
b101 #
#120
b100 ,
b10 $
b10 +
b10 &
b10 *
b110 "
b110 #
#140
b100 ,
b1 $
b1 +
b11 &
b11 *
b111 "
b111 #
