DSD/Week-1/A2.v
module A2(f,x1,x2,x3,x4);
input x1,x2,x3,x4;
output f;
assign f = (x1&x2&x4)|(x2&x3&x4)|(x1&x3&x4)|(x1&x2&x3);
endmodule

DSD/Week-1/A2_tb.v
`timescale 1ns/1ns
`include "A2.v"

module A2_tb();
reg a,b,c,d;
wire f;

A2 a2(f,a,b,c,d);
initial begin
	$dumpfile("A2_tb.vcd");
	$dumpvars(0,A2_tb);
	a=0;b=0;c=0;d=0;#20;
	a=0;b=0;c=0;d=1;#20;
	a=0;b=0;c=1;d=0;#20;
	a=0;b=0;c=1;d=1;#20;
	a=0;b=1;c=0;d=0;#20;
	a=0;b=1;c=0;d=1;#20;
	a=0;b=1;c=1;d=0;#20;
	a=0;b=1;c=1;d=1;#20;
	a=1;b=0;c=0;d=0;#20;
	a=1;b=0;c=0;d=1;#20;
	a=1;b=0;c=1;d=0;#20;
	a=1;b=0;c=1;d=1;#20;
	a=1;b=1;c=0;d=0;#20;
	a=1;b=1;c=0;d=1;#20;
	a=1;b=1;c=1;d=0;#20;
	a=1;b=1;c=1;d=1;#20;
	$display("Test complete");
end
endmodule

DSD/Week-1/A2_tb.vcd
$date
	Mon Sep 18 00:10:24 2023
$end
$version
	Icarus Verilog
$end
$timescale
	1ns
$end
$scope module A2_tb $end
$var wire 1 ! f $end
$var reg 1 " a $end
$var reg 1 # b $end
$var reg 1 $ c $end
$var reg 1 % d $end
$scope module a2 $end
$var wire 1 ! f $end
$var wire 1 " x1 $end
$var wire 1 # x2 $end
$var wire 1 $ x3 $end
$var wire 1 % x4 $end
$upscope $end
$upscope $end
$enddefinitions $end
#0
$dumpvars
0%
0$
0#
0"
0!
$end
#20
1%
#40
0%
1$
#60
1%
#80
0%
0$
1#
#100
1%
#120
0%
1$
#140
1!
1%
#160
0!
0%
0$
0#
1"
#180
1%
#200
0%
1$
#220
1!
1%
#240
0!
0%
0$
1#
#260
1!
1%
#280
0%
1$
#300
1%
