DSD labs/Week-1/Q2a.v
module Q2a(f,a,b,c,d);
input a,b,c,d;
output f;
assign f = (b&c) | (c&~d) | (~b&c) | (~a&b&d);
endmodule

DSD/Week-1/Q2a_tb.v
`timescale 1ns/1ns
`include "Q2a.v"

module Q2a_tb();
reg a,b,c,d;
wire f;

Q2a q2a(f,a,b,c,d);
initial begin
	$dumpfile("Q2a_tb.vcd");
	$dumpvars(0,Q2a_tb);
	a=0;b=0;c=0;d=0;#20;
	a=0;b=0;c=0;d=1;#20;
	a=0;b=0;c=1;d=0;#20;
	a=0;b=0;c=1;d=1;#20;
	a=0;b=1;c=0;d=0;#20;
	a=0;b=1;c=0;d=1;#20;
	a=0;b=1;c=1;d=0;#20;
	a=0;b=1;c=0;d=1;#20;
	a=1;b=0;c=0;d=0;#20;
	a=1;b=0;c=0;d=1;#20;
	a=1;b=0;c=1;d=0;#20;
	a=1;b=0;c=1;d=1;#20;
	a=1;b=1;c=0;d=0;#20;
	a=1;b=1;c=0;d=1;#20;
	a=1;b=1;c=1;d=0;#20;
	a=1;b=1;c=0;d=1;#20;
	$display("Test complete");
end
endmodule

DSD/Week-1/Q2a_tb.vcd
$date
	Sun Sep 17 23:50:53 2023
$end
$version
	Icarus Verilog
$end
$timescale
	1ns
$end
$scope module Q2a_tb $end
$var wire 1 ! f $end
$var reg 1 " a $end
$var reg 1 # b $end
$var reg 1 $ c $end
$var reg 1 % d $end
$scope module q2a $end
$var wire 1 " a $end
$var wire 1 # b $end
$var wire 1 $ c $end
$var wire 1 % d $end
$var wire 1 ! f $end
$upscope $end
$upscope $end
$enddefinitions $end
#0
$dumpvars
0%
0$
0#
0"
0!
$end
#20
1%
#40
1!
0%
1$
#60
1%
#80
0!
0%
0$
1#
#100
1!
1%
#120
1!
0%
1$
#140
1%
0$
#160
0!
0%
0#
1"
#180
1%
#200
1!
0%
1$
#220
1%
#240
0!
0%
0$
1#
#260
1%
#280
1!
0%
1$
#300
0!
1%
0$
